{"name":"Bogdan Bogdanovic","team_acronym":"sac","team_name":"Sacramento Kings","games_played":"42","minutes_per_game":"26:37","field_goals_attempted_per_game":"8.9","field_goals_made_per_game":"4.4","field_goal_percentage":"48.9","free_throw_percentage":"82.4","three_point_attempted_per_game":"3.7","three_point_made_per_game":"1.5","three_point_percentage":"40.1","points_per_game":"11.5","offensive_rebounds_per_game":"0.4","defensive_rebounds_per_game":"2.3","rebounds_per_game":"2.7","assists_per_game":"2.8","steals_per_game":"1.0","blocks_per_game":"0.2","turnovers_per_game":"1.7","player_efficiency_rating":"2.1"}