{"name":"Cody Zeller","team_acronym":"cha","team_name":"Charlotte Hornets","games_played":"19","minutes_per_game":"19:54","field_goals_attempted_per_game":"5.0","field_goals_made_per_game":"2.5","field_goal_percentage":"49.5","free_throw_percentage":"72.4","three_point_attempted_per_game":"0.1","three_point_made_per_game":"0.1","three_point_percentage":"100.0","points_per_game":"7.2","offensive_rebounds_per_game":"2.4","defensive_rebounds_per_game":"3.1","rebounds_per_game":"5.5","assists_per_game":"0.8","steals_per_game":"0.5","blocks_per_game":"1.1","turnovers_per_game":"1.1","player_efficiency_rating":"2.7"}