{"name":"David West","team_acronym":"gsw","team_name":"Golden State Warriors","games_played":"44","minutes_per_game":"13:17","field_goals_attempted_per_game":"5.0","field_goals_made_per_game":"3.0","field_goal_percentage":"60.6","free_throw_percentage":"70.0","three_point_attempted_per_game":"0.2","three_point_made_per_game":"0.1","three_point_percentage":"42.9","points_per_game":"7.0","offensive_rebounds_per_game":"0.9","defensive_rebounds_per_game":"2.5","rebounds_per_game":"3.4","assists_per_game":"1.8","steals_per_game":"0.6","blocks_per_game":"1.1","turnovers_per_game":"1.0","player_efficiency_rating":"1.6"}