{"name":"Jakob Poeltl","team_acronym":"tor","team_name":"Toronto Raptors","games_played":"46","minutes_per_game":"17:31","field_goals_attempted_per_game":"4.6","field_goals_made_per_game":"3.0","field_goal_percentage":"64.8","free_throw_percentage":"51.5","three_point_attempted_per_game":"0.0","three_point_made_per_game":"0.0","three_point_percentage":"50.0","points_per_game":"6.8","offensive_rebounds_per_game":"2.1","defensive_rebounds_per_game":"2.6","rebounds_per_game":"4.7","assists_per_game":"0.5","steals_per_game":"0.4","blocks_per_game":"1.1","turnovers_per_game":"0.8","player_efficiency_rating":"2.7"}