{"name":"Jason Terry","team_acronym":"mil","team_name":"Milwaukee Bucks","games_played":"15","minutes_per_game":"9:38","field_goals_attempted_per_game":"1.7","field_goals_made_per_game":"0.5","field_goal_percentage":"32.0","free_throw_percentage":"100.0","three_point_attempted_per_game":"1.0","three_point_made_per_game":"0.1","three_point_percentage":"13.3","points_per_game":"1.3","offensive_rebounds_per_game":"0.0","defensive_rebounds_per_game":"0.8","rebounds_per_game":"0.8","assists_per_game":"0.5","steals_per_game":"0.6","blocks_per_game":"0.3","turnovers_per_game":"0.3","player_efficiency_rating":"0.9"}