{"name":"Jerian Grant","team_acronym":"chi","team_name":"Chicago Bulls","games_played":"45","minutes_per_game":"21:12","field_goals_attempted_per_game":"6.5","field_goals_made_per_game":"2.7","field_goal_percentage":"41.0","free_throw_percentage":"71.3","three_point_attempted_per_game":"2.4","three_point_made_per_game":"0.7","three_point_percentage":"29.6","points_per_game":"7.6","offensive_rebounds_per_game":"0.4","defensive_rebounds_per_game":"1.9","rebounds_per_game":"2.2","assists_per_game":"4.6","steals_per_game":"0.7","blocks_per_game":"0.1","turnovers_per_game":"1.1","player_efficiency_rating":"1.8"}