{"name":"Jrue Holiday","team_acronym":"nor","team_name":"New Orleans Pelicans","games_played":"44","minutes_per_game":"36:54","field_goals_attempted_per_game":"14.7","field_goals_made_per_game":"7.3","field_goal_percentage":"49.7","free_throw_percentage":"80.3","three_point_attempted_per_game":"5.0","three_point_made_per_game":"1.7","three_point_percentage":"34.2","points_per_game":"18.6","offensive_rebounds_per_game":"0.6","defensive_rebounds_per_game":"3.8","rebounds_per_game":"4.4","assists_per_game":"5.1","steals_per_game":"1.5","blocks_per_game":"0.6","turnovers_per_game":"2.7","player_efficiency_rating":"2.3"}