{"name":"Marco Belinelli","team_acronym":"atl","team_name":"Atlanta Hawks","games_played":"43","minutes_per_game":"23:17","field_goals_attempted_per_game":"9.4","field_goals_made_per_game":"4.0","field_goal_percentage":"42.1","free_throw_percentage":"92.0","three_point_attempted_per_game":"4.7","three_point_made_per_game":"1.8","three_point_percentage":"38.7","points_per_game":"11.6","offensive_rebounds_per_game":"0.3","defensive_rebounds_per_game":"1.7","rebounds_per_game":"2.0","assists_per_game":"2.0","steals_per_game":"1.0","blocks_per_game":"0.1","turnovers_per_game":"1.1","player_efficiency_rating":"0.8"}