{"name":"Nikola Mirotic","team_acronym":"chi","team_name":"Chicago Bulls","games_played":"20","minutes_per_game":"24:58","field_goals_attempted_per_game":"12.5","field_goals_made_per_game":"6.1","field_goal_percentage":"49.0","free_throw_percentage":"78.5","three_point_attempted_per_game":"6.4","three_point_made_per_game":"2.9","three_point_percentage":"45.7","points_per_game":"17.7","offensive_rebounds_per_game":"0.9","defensive_rebounds_per_game":"5.9","rebounds_per_game":"6.8","assists_per_game":"1.6","steals_per_game":"0.6","blocks_per_game":"0.5","turnovers_per_game":"1.3","player_efficiency_rating":"1.9"}