{"name":"Rudy Gobert","team_acronym":"uth","team_name":"Utah Jazz","games_played":"22","minutes_per_game":"30:06","field_goals_attempted_per_game":"7.5","field_goals_made_per_game":"4.4","field_goal_percentage":"58.8","free_throw_percentage":"65.5","three_point_attempted_per_game":"0.0","three_point_made_per_game":"0.0","three_point_percentage":"0.0","points_per_game":"12.2","offensive_rebounds_per_game":"2.6","defensive_rebounds_per_game":"7.0","rebounds_per_game":"9.6","assists_per_game":"1.1","steals_per_game":"0.6","blocks_per_game":"2.5","turnovers_per_game":"1.9","player_efficiency_rating":"2.6"}